jobspy2/__init__.py
jobspy2/jobs/__init__.py
jobspy2/scrapers/__init__.py
jobspy2/scrapers/exceptions.py
jobspy2/scrapers/utils.py
jobspy2/scrapers/glassdoor/__init__.py
jobspy2/scrapers/glassdoor/constants.py
jobspy2/scrapers/google/__init__.py
jobspy2/scrapers/google/constants.py
jobspy2/scrapers/indeed/__init__.py
jobspy2/scrapers/indeed/constants.py
jobspy2/scrapers/linkedin/__init__.py
jobspy2/scrapers/linkedin/constants.py
jobspy2/scrapers/ziprecruiter/__init__.py
jobspy2/scrapers/ziprecruiter/constants.py
jobspy2-0.0.8.dist-info/METADATA
jobspy2-0.0.8.dist-info/WHEEL
jobspy2-0.0.8.dist-info/RECORD
