Metadata-Version: 2.4
Name: jobspy2
Version: 0.0.8
Summary: Scrape job posting from different job boards
Project-URL: Repository, https://github.com/FranciscoMoretti/jobsparser
Author-email: Francisco Moretti <franciscoemoretti@gmail.com>
Keywords: python
Classifier: Intended Audience :: Developers
Classifier: Programming Language :: Python
Classifier: Programming Language :: Python :: 3
Classifier: Programming Language :: Python :: 3.9
Classifier: Programming Language :: Python :: 3.10
Classifier: Programming Language :: Python :: 3.11
Classifier: Programming Language :: Python :: 3.12
Classifier: Programming Language :: Python :: 3.13
Classifier: Topic :: Software Development :: Libraries :: Python Modules
Requires-Python: <4.0,>=3.9
Requires-Dist: beautifulsoup4>=4.12.2
Requires-Dist: markdownify>=0.13.1
Requires-Dist: numpy==1.26.3
Requires-Dist: pandas>=2.1.0
Requires-Dist: pydantic>=2.3.0
Requires-Dist: regex>=2024.4.28
Requires-Dist: requests>=2.31.0
Requires-Dist: tls-client>=1.0.1
